django_email_test
