Metadata-Version: 1.0
Name: django-email-test
Version: 0.0.3
Summary: An app for sending test emails via the admin site to make sure your email server is working.
Home-page: http://seanhayes.name/
Author: Seán Hayes
Author-email: sean@seanhayes.name
License: BSD
Download-URL: https://github.com/SeanHayes/django-email-test
Keywords: django admin email test
Platform: UNKNOWN
Classifier: Development Status :: 3 - Alpha
Classifier: Framework :: Django
Classifier: Intended Audience :: Developers
Classifier: Intended Audience :: System Administrators
Classifier: License :: OSI Approved :: BSD License
Classifier: Operating System :: OS Independent
Classifier: Programming Language :: Python
Classifier: Programming Language :: Python :: 2.6
Classifier: Topic :: Internet :: WWW/HTTP :: Dynamic Content
Classifier: Topic :: Internet :: WWW/HTTP :: Site Management
Classifier: Topic :: Software Development :: Libraries
Classifier: Topic :: Software Development :: Libraries :: Python Modules
